odoo/addons/edi_xml/README.rst
odoo/addons/edi_xml/__init__.py
odoo/addons/edi_xml/__manifest__.py
odoo/addons/edi_xml/xmler.py
odoo/addons/edi_xml/components/__init__.py
odoo/addons/edi_xml/components/xml_handler.py
odoo/addons/edi_xml/i18n/edi_xml.pot
odoo/addons/edi_xml/readme/CONTRIBUTORS.rst
odoo/addons/edi_xml/readme/DESCRIPTION.rst
odoo/addons/edi_xml/static/description/icon.png
odoo/addons/edi_xml/static/description/index.html
odoo/addons/edi_xml/tests/__init__.py
odoo/addons/edi_xml/tests/common.py
odoo/addons/edi_xml/tests/test_xml.py
odoo/addons/edi_xml/tests/fixtures/Test.xsd
odoo13_addon_edi_xml-13.0.1.2.2.dist-info/METADATA
odoo13_addon_edi_xml-13.0.1.2.2.dist-info/WHEEL
odoo13_addon_edi_xml-13.0.1.2.2.dist-info/top_level.txt
odoo13_addon_edi_xml-13.0.1.2.2.dist-info/RECORD
